proxy_checker_httpx/__init__.py
proxy_checker_httpx/proxy_checker.py
proxy_checker_httpx-0.6.0.dist-info/LICENSE.md
proxy_checker_httpx-0.6.0.dist-info/METADATA
proxy_checker_httpx-0.6.0.dist-info/WHEEL
proxy_checker_httpx-0.6.0.dist-info/top_level.txt
proxy_checker_httpx-0.6.0.dist-info/RECORD
