Metadata-Version: 2.1
Name: proxy-checker-httpx
Version: 0.6.0
Summary: Proxy checker in Python
Author: Maehdakvan
Project-URL: Source Code, https://github.com/DedInc/proxy-checker-python
Keywords: proxy checker
Classifier: License :: OSI Approved :: MIT License
License-File: LICENSE.md
Requires-Dist: httpx
